[{"name": "kilowattrel", "id": 941, "height": 14, "weight": 386, "is_default": true}, {"name": "maschiff", "id": 942, "height": 5, "weight": 160, "is_default": true}, {"name": "mabosstiff", "id": 943, "height": 11, "weight": 610, "is_default": true}, {"name": "shroodle", "id": 944, "height": 2, "weight": 7, "is_default": true}, {"name": "grafaiai", "id": 945, "height": 7, "weight": 272, "is_default": true}, {"name": "bramblin", "id": 946, "height": 6, "weight": 6, "is_default": true}, {"name": "brambleghast", "id": 947, "height": 12, "weight": 60, "is_default": true}, {"name": "toedscool", "id": 948, "height": 9, "weight": 330, "is_default": true}, {"name": "toedscruel", "id": 949, "height": 19, "weight": 580, "is_default": true}, {"name": "klawf", "id": 950, "height": 13, "weight": 790, "is_default": true}, {"name": "capsakid", "id": 951, "height": 3, "weight": 30, "is_default": true}, {"name": "scovillain", "id": 952, "height": 9, "weight": 150, "is_default": true}, {"name": "rellor", "id": 953, "height": 2, "weight": 10, "is_default": true}, {"name": "rabsca", "id": 954, "height": 3, "weight": 35, "is_default": true}, {"name": "flittle", "id": 955, "height": 2, "weight": 15, "is_default": true}, {"name": "espathra", "id": 956, "height": 19, "weight": 900, "is_default": true}, {"name": "tinkatink", "id": 957, "height": 4, "weight": 89, "is_default": true}, {"name": "tinkatuff", "id": 958, "height": 7, "weight": 591, "is_default": true}, {"name": "tinkaton", "id": 959, "height": 7, "weight": 1128, "is_default": true}, {"name": "wiglett", "id": 960, "height": 12, "weight": 18, "is_default": true}]