[{"name": "weavile", "id": 461, "height": 11, "weight": 340, "is_default": true}, {"name": "magnezone", "id": 462, "height": 12, "weight": 1800, "is_default": true}, {"name": "lickilicky", "id": 463, "height": 17, "weight": 1400, "is_default": true}, {"name": "rhyperior", "id": 464, "height": 24, "weight": 2828, "is_default": true}, {"name": "tangrowth", "id": 465, "height": 20, "weight": 1286, "is_default": true}, {"name": "electivire", "id": 466, "height": 18, "weight": 1386, "is_default": true}, {"name": "magmortar", "id": 467, "height": 16, "weight": 680, "is_default": true}, {"name": "togekiss", "id": 468, "height": 15, "weight": 380, "is_default": true}, {"name": "yanmega", "id": 469, "height": 19, "weight": 515, "is_default": true}, {"name": "leafeon", "id": 470, "height": 10, "weight": 255, "is_default": true}, {"name": "glaceon", "id": 471, "height": 8, "weight": 259, "is_default": true}, {"name": "gliscor", "id": 472, "height": 20, "weight": 425, "is_default": true}, {"name": "mamoswine", "id": 473, "height": 25, "weight": 2910, "is_default": true}, {"name": "porygon-z", "id": 474, "height": 9, "weight": 340, "is_default": true}, {"name": "gallade", "id": 475, "height": 16, "weight": 520, "is_default": true}, {"name": "probopass", "id": 476, "height": 14, "weight": 3400, "is_default": true}, {"name": "dusknoir", "id": 477, "height": 22, "weight": 1066, "is_default": true}, {"name": "froslass", "id": 478, "height": 13, "weight": 266, "is_default": true}, {"name": "rotom", "id": 479, "height": 3, "weight": 3, "is_default": true}, {"name": "uxie", "id": 480, "height": 3, "weight": 3, "is_default": true}]