[{"name": "tornadus-incarnate", "id": 641, "height": 15, "weight": 630, "is_default": true}, {"name": "thundurus-incarnate", "id": 642, "height": 15, "weight": 610, "is_default": true}, {"name": "reshiram", "id": 643, "height": 32, "weight": 3300, "is_default": true}, {"name": "zekrom", "id": 644, "height": 29, "weight": 3450, "is_default": true}, {"name": "landorus-incarnate", "id": 645, "height": 15, "weight": 680, "is_default": true}, {"name": "kyurem", "id": 646, "height": 30, "weight": 3250, "is_default": true}, {"name": "keldeo-ordinary", "id": 647, "height": 14, "weight": 485, "is_default": true}, {"name": "meloetta-aria", "id": 648, "height": 6, "weight": 65, "is_default": true}, {"name": "genesect", "id": 649, "height": 15, "weight": 825, "is_default": true}, {"name": "chespin", "id": 650, "height": 4, "weight": 90, "is_default": true}, {"name": "quilladin", "id": 651, "height": 7, "weight": 290, "is_default": true}, {"name": "chesnaught", "id": 652, "height": 16, "weight": 900, "is_default": true}, {"name": "fennekin", "id": 653, "height": 4, "weight": 94, "is_default": true}, {"name": "braixen", "id": 654, "height": 10, "weight": 145, "is_default": true}, {"name": "delphox", "id": 655, "height": 15, "weight": 390, "is_default": true}, {"name": "froakie", "id": 656, "height": 3, "weight": 70, "is_default": true}, {"name": "frogadier", "id": 657, "height": 6, "weight": 109, "is_default": true}, {"name": "greninja", "id": 658, "height": 15, "weight": 400, "is_default": true}, {"name": "bunnelby", "id": 659, "height": 4, "weight": 50, "is_default": true}, {"name": "diggersby", "id": 660, "height": 10, "weight": 424, "is_default": true}]